async_scheduler_object/__init__.py
async_scheduler_object-1.1.0.dist-info/WHEEL
async_scheduler_object-1.1.0.dist-info/METADATA
async_scheduler_object-1.1.0.dist-info/RECORD
