Metadata-Version: 2.1
Name: async-scheduler-object
Version: 1.1.0
Summary: Object-like async scheduler
Home-page: https://github.com/LEv145/async-scheduler-object
License: MIT
Author: LEv145
Author-email: you@example.com
Requires-Python: >=3.7,<4.0
Classifier: License :: OSI Approved :: MIT License
Classifier: Programming Language :: Python :: 3
Classifier: Programming Language :: Python :: 3.7
Classifier: Programming Language :: Python :: 3.8
Classifier: Programming Language :: Python :: 3.9
Classifier: Programming Language :: Python :: 3.10
Classifier: Programming Language :: Python :: 3.11
Project-URL: Repository, https://github.com/LEv145/async-scheduler-object
